{
    "key": "publicacao_c",
    "title": "Publica<C3><A7><C3><A3>o",
    "fields": [
        {
            "key": "publicacao_c_i",
            "label": "Imagem",
            "name": "imagem",
            "type": "image",
            "instructions": "",
            "required": false,
            "conditional_logic": false,
            "wrapper": {
                "width": "20%",
                "class": "",
                "id": ""
            },
            "return_format": "array",
            "preview_size": "vertical",
            "library": "all",
            "min_width": 0,
            "min_height": 0,
            "min_size": 0,
            "max_width": 0,
            "max_height": 0,
            "max_size": 0,
            "mime_types": ""
        },
        {
            "key": "publicacao_c_t",
            "label": "Descri<C3><A7><C3><A3>o",
            "name": "descricao",
            "type": "textarea",
            "instructions": "",
            "required": false,
            "conditional_logic": false,
            "wrapper": {
                "width": "80%",
                "class": "",
                "id": ""
            },
            "new_lines": "br",
            "rows": 6,
            "default_value": "",
            "maxlength": "",
            "placeholder": ""
        },
        {
            "key": "publicacao_c_botoes_c_l",
            "label": "Itens",
            "name": "itens",
            "type": "repeater",
            "instructions": "",
            "required": false,
            "conditional_logic": false,
            "wrapper": {
                "width": "",
                "class": "",
                "id": ""
            },
            "layout": "table",
            "min": 1,
            "max": 0,
            "button_label": "",
            "collapsed": "",
            "sub_fields": [
                {
                    "key": "publicacao_c_botoes_c_l_tt",
                    "label": "Link",
                    "name": "link",
                    "type": "link",
                    "instructions": "",
                    "required": false,
                    "conditional_logic": false,
                    "wrapper": {
                        "width": "",
                        "class": "",
                        "id": ""
                    },
                    "return_format": "array"
                }
            ]
        }
    ],
    "location": [
        [
            {
                "param": "post_type",
                "operator": "==",
                "value": "publicacao"
            }
        ]
    ],
    "menu_order": 1,
    "position": "normal",
    "style": "seamless",
    "label_placement": "top",
    "instruction_placement": "label",
    "hide_on_screen": [],
    "active": true,
    "description": "",
    "modified": 1696444957
}
